{
  "id": 451,
  "slug": "his-robe-of-honor",
  "title": "His Robe of Honor",
  "formatted_title": "His Robe of Honor",
  "html_title": "<span class=\"work-title\">His Robe of Honor</span>",
  "work_type": "novel",
  "publication_year": 1916,
  "plot_summary": null,
  "literary_significance": null,
  "attribution_notes": "co-writer James Dorrance",
  "author": {
    "id": 200,
    "slug": "ethel-smith-dorrance",
    "name": "Ethel Smith Dorrance",
    "birth_year": 1880,
    "death_year": null,
    "film_count": 3
  },
  "stats": {
    "adaptation_count": 1,
    "year_span": 0,
    "is_remake_champion": false,
    "average_gap_between_adaptations": null
  },
  "patterns": {
    "is_speed_demon": false,
    "speed_demon_delay": 2,
    "is_remake_champion": false,
    "remake_champion_rank": null
  },
  "adaptations": [
    {
      "id": 521,
      "slug": "his-robe-of-honor-1918",
      "title": "His Robe of Honor",
      "html_title": "<span class=\"film-title\">His Robe of Honor</span>",
      "year": 1918,
      "studio": "Paralta Plays",
      "directors": "Rex Ingram",
      "genres": [
        "Drama"
      ],
      "has_media": true,
      "years_after_publication": 2
    }
  ],
  "adaptation_gaps": [],
  "has_photoplay_edition": false,
  "magazine_publication": null,
  "external_urls": [],
  "external_ids": {
    "gutenberg_id": null,
    "internet_archive_id": null,
    "openlibrary_id": null,
    "oclc_number": null,
    "wikidata_id": null,
    "viaf_id": null
  },
  "has_narrative": false,
  "last_updated": "2025-08-04T17:06:35.659603"
}