{
  "id": 752,
  "slug": "mother",
  "title": "Mother",
  "formatted_title": "Mother",
  "html_title": "<span class=\"work-title\">Mother</span>",
  "work_type": "novel",
  "publication_year": 1911,
  "plot_summary": null,
  "plot_summary_html": "",
  "literary_significance": null,
  "literary_significance_html": "",
  "attribution_notes": null,
  "author": {
    "id": 376,
    "slug": "kathleen-norris",
    "name": "Kathleen Norris",
    "birth_year": 1880,
    "death_year": 1966,
    "film_count": 19
  },
  "stats": {
    "adaptation_count": 1,
    "year_span": 0,
    "is_remake_champion": false,
    "average_gap_between_adaptations": null
  },
  "patterns": {
    "is_speed_demon": false,
    "speed_demon_delay": 16,
    "is_remake_champion": false,
    "remake_champion_rank": null
  },
  "adaptations": [
    {
      "id": 843,
      "slug": "mother-1927",
      "title": "Mother",
      "html_title": "<span class=\"film-title\">Mother</span>",
      "year": 1927,
      "studio": "Robertson-Cole",
      "directors": "J. Leo Meehan",
      "genres": [
        "Melodrama"
      ],
      "has_media": true,
      "years_after_publication": 16
    }
  ],
  "adaptation_gaps": [],
  "has_photoplay_edition": false,
  "magazine_publication": null,
  "external_urls": [],
  "external_ids": {
    "gutenberg_id": null,
    "internet_archive_id": null,
    "openlibrary_id": null,
    "oclc_number": null,
    "wikidata_id": "Q125531123",
    "viaf_id": null
  },
  "has_narrative": false,
  "last_updated": "2025-08-04T17:06:35.659603"
}