{
  "id": 535,
  "slug": "the-leavenworth-case",
  "title": "The Leavenworth Case",
  "formatted_title": "The Leavenworth Case",
  "html_title": "<span class=\"work-title\">The Leavenworth Case</span>",
  "work_type": "novel",
  "publication_year": 1878,
  "plot_summary": null,
  "plot_summary_html": "",
  "literary_significance": null,
  "literary_significance_html": "",
  "attribution_notes": null,
  "author": {
    "id": 243,
    "slug": "anna-katharine-green",
    "name": "Anna Katharine Green",
    "birth_year": 1846,
    "death_year": 1935,
    "film_count": 4
  },
  "stats": {
    "adaptation_count": 2,
    "year_span": 13,
    "is_remake_champion": false,
    "photoplay_edition_count": 1,
    "average_gap_between_adaptations": 13
  },
  "patterns": {
    "is_speed_demon": false,
    "speed_demon_delay": 45,
    "is_remake_champion": false,
    "remake_champion_rank": null
  },
  "adaptations": [
    {
      "id": 611,
      "slug": "the-leavenworth-case-1923",
      "title": "The Leavenworth Case",
      "html_title": "<span class=\"film-title\">The Leavenworth Case</span>",
      "year": 1923,
      "studio": "Whitman Bennett Productions",
      "directors": "Charles Giblyn",
      "genres": [
        "Melodrama",
        "Mystery"
      ],
      "has_media": true,
      "years_after_publication": 45
    },
    {
      "id": 612,
      "slug": "the-leavenworth-case-1936",
      "title": "The Leavenworth Case",
      "html_title": "<span class=\"film-title\">The Leavenworth Case</span>",
      "year": 1936,
      "studio": "Republic",
      "directors": "Lewis D. Collins",
      "genres": [
        "Comedy-drama",
        "Mystery"
      ],
      "has_media": true,
      "years_after_publication": 58
    }
  ],
  "adaptation_gaps": [
    {
      "from_year": 1923,
      "to_year": 1936,
      "gap_years": 13
    }
  ],
  "photoplay_editions": [
    {
      "id": 258,
      "source_work_id": 535,
      "film_id": 611,
      "publisher": "A.L. Burt",
      "edition_year": 1923,
      "edition_description": null,
      "binding_type": "HB",
      "dust_jacket": "True",
      "cover_type": "photo front DJ",
      "photo_content": "4 stills",
      "price_low_cents": 800,
      "price_high_cents": 3000,
      "source_url": null,
      "source_notes": "Davis 2002",
      "verified": "False",
      "created_at": "2025-08-16T20:45:36.108924",
      "updated_at": "2025-08-16T23:38:00.316442",
      "ia_url": null,
      "has_visual_content": "True",
      "country": "US",
      "media": []
    }
  ],
  "magazine_publication": null,
  "external_urls": [],
  "external_ids": {
    "gutenberg_id": null,
    "internet_archive_id": null,
    "openlibrary_id": null,
    "oclc_number": null,
    "wikidata_id": "Q16936995",
    "viaf_id": null
  },
  "last_updated": "2025-08-16T17:41:38.223064"
}