{
  "id": 289,
  "slug": "ride-the-pink-horse-1947",
  "title": "Ride the Pink Horse",
  "formatted_title": "Ride the Pink Horse",
  "html_title": "<span class=\"film-title\">Ride the Pink Horse</span>",
  "release_year": 1947,
  "runtime_minutes": 95,
  "country_of_production": "United States",
  "genres": [
    "Film noir"
  ],
  "studio": "Universal-International",
  "production_companies": "Universal-International Pictures Co., Inc.",
  "distribution_companies": "Universal Pictures Company, Inc.",
  "directors": "Robert Montgomery",
  "writers": "Ben Hecht|Charles Lederer",
  "cast_members": "Robert Montgomery|Thomas Gomez|Rita Conde|Iris Flores|Wanda Hendrix|Grandon Rhodes|Tito Renaldo|Richard Gaines|Andrea King|Martin Garralaga",
  "color_info": "black-and-white",
  "adaptation_notes": null,
  "afi_catalog_id": 25321,
  "source_work": {
    "id": 242,
    "slug": "ride-the-pink-horse",
    "title": "Ride the Pink Horse",
    "formatted_title": "Ride the Pink Horse",
    "html_title": "<span class=\"work-title\">Ride the Pink Horse</span>",
    "work_type": "novel",
    "publication_year": 1946,
    "genre": null,
    "plot_summary": null,
    "literary_significance": null,
    "adaptation_count": 1,
    "year_to_adaptation": 1
  },
  "author": {
    "id": 78,
    "slug": "dorothy-b-hughes",
    "name": "Dorothy B. Hughes",
    "birth_year": 1904,
    "death_year": 1993,
    "nationality": "United States",
    "film_count": 3
  },
  "other_adaptations": [],
  "adaptation_context": null,
  "media": [
    {
      "id": 791,
      "media_type": "advertisement",
      "title": "1947 - Earle Theater - 14 Nov MC - Allentown PA.jpg",
      "caption": "Earle Theate",
      "url": "https://upload.wikimedia.org/wikipedia/commons/1/1d/1947_-_Earle_Theater_-_14_Nov_MC_-_Allentown_PA.jpg",
      "thumbnail_url": "https://upload.wikimedia.org/wikipedia/commons/thumb/1/1d/1947_-_Earle_Theater_-_14_Nov_MC_-_Allentown_PA.jpg/300px-1947_-_Earle_Theater_-_14_Nov_MC_-_Allentown_PA.jpg",
      "source": "wikimedia",
      "source_url": "https://commons.wikimedia.org/wiki/File:1947_-_Earle_Theater_-_14_Nov_MC_-_Allentown_PA.jpg",
      "license": "public_domain",
      "attribution": "Self Scanned",
      "is_featured": "False"
    }
  ],
  "has_media": true,
  "media_count": 1,
  "has_narrative": false,
  "last_updated": "2025-07-18T18:36:32.713708"
}