{
  "id": 554,
  "slug": "come-and-get-it-1936",
  "title": "Come and Get It",
  "formatted_title": "Come and Get It",
  "html_title": "<span class=\"film-title\">Come and Get It</span>",
  "release_year": 1936,
  "runtime_minutes": 105,
  "country_of_production": "United States",
  "genres": [
    "Drama"
  ],
  "studio": "Howard Productions",
  "production_companies": "Howard Productions, Inc.",
  "distribution_companies": "United Artists Corp.",
  "directors": "Howard Hawks|William Wyler",
  "writers": "Jane Murfin|Jules Furthman",
  "cast_members": "Edward Arnold|Joel McCrea|Frances Farmer|Walter Brennan|Andrea Leeds|Frank Shields|Mady Christians|Mary Nash|Clem Bevans|Edwin Maxwell",
  "color_info": "black-and-white",
  "availability": null,
  "adaptation_notes": null,
  "afi_catalog_id": 4165,
  "source_work": {
    "id": 482,
    "slug": "come-and-get-it",
    "title": "Come and Get It",
    "formatted_title": "Come and Get It",
    "html_title": "<span class=\"work-title\">Come and Get It</span>",
    "work_type": "novel",
    "publication_year": 1934,
    "plot_summary": null,
    "plot_summary_html": "",
    "literary_significance": null,
    "literary_significance_html": "",
    "adaptation_count": 1,
    "year_to_adaptation": 2
  },
  "author": {
    "id": 40,
    "slug": "edna-ferber",
    "name": "Edna Ferber",
    "birth_year": 1885,
    "death_year": 1968,
    "nationality": "American",
    "film_count": 25
  },
  "other_adaptations": [],
  "adaptation_context": null,
  "media": [
    {
      "id": 1269,
      "media_type": "poster",
      "title": "月缺難圓 香港華字日報 19380213.png",
      "caption": "Come and Get It (1936) poster",
      "url": "https://upload.wikimedia.org/wikipedia/commons/8/8a/%E6%9C%88%E7%BC%BA%E9%9B%A3%E5%9C%93_%E9%A6%99%E6%B8%AF%E8%8F%AF%E5%AD%97%E6%97%A5%E5%A0%B1_19380213.png",
      "thumbnail_url": "https://upload.wikimedia.org/wikipedia/commons/thumb/8/8a/%E6%9C%88%E7%BC%BA%E9%9B%A3%E5%9C%93_%E9%A6%99%E6%B8%AF%E8%8F%AF%E5%AD%97%E6%97%A5%E5%A0%B1_19380213.png/300px-%E6%9C%88%E7%BC%BA%E9%9B%A3%E5%9C%93_%E9%A6%99%E6%B8%AF%E8%8F%AF%E5%AD%97%E6%97%A5%E5%A0%B1_19380213.png",
      "source": "Wikimedia Commons",
      "source_url": "https://commons.wikimedia.org/wiki/File:月缺難圓_香港華字日報_19380213.png",
      "license": "public_domain",
      "attribution": "香港華字日報",
      "is_featured": "True"
    },
    {
      "id": 3936,
      "media_type": "poster",
      "title": "Come and Get It (1936) - Poster",
      "caption": "Theatrical poster for Come and Get It (1936)",
      "url": "https://image.tmdb.org/t/p/original/1XrclgIlth8nt2Hh7gl3LpRyCfV.jpg",
      "thumbnail_url": "https://image.tmdb.org/t/p/w342/1XrclgIlth8nt2Hh7gl3LpRyCfV.jpg",
      "source": "TMDb",
      "source_url": "https://www.themoviedb.org/movie/93313",
      "license": "fair_use",
      "attribution": "Howard Productions",
      "is_featured": "True"
    },
    {
      "id": 3937,
      "media_type": "poster",
      "title": "Come and Get It (1936) - Poster",
      "caption": "Theatrical poster for Come and Get It (1936)",
      "url": "https://image.tmdb.org/t/p/original/cy4wlhy0a7VxKCJO4tHKnNCC3Vb.jpg",
      "thumbnail_url": "https://image.tmdb.org/t/p/w342/cy4wlhy0a7VxKCJO4tHKnNCC3Vb.jpg",
      "source": "TMDb",
      "source_url": "https://www.themoviedb.org/movie/93313",
      "license": "fair_use",
      "attribution": "Howard Productions",
      "is_featured": "False"
    },
    {
      "id": 3938,
      "media_type": "poster",
      "title": "Come and Get It (1936) - Poster",
      "caption": "Theatrical poster for Come and Get It (1936)",
      "url": "https://image.tmdb.org/t/p/original/4w65AMsJ0RZVkxGfxw4DVWWSTyq.jpg",
      "thumbnail_url": "https://image.tmdb.org/t/p/w342/4w65AMsJ0RZVkxGfxw4DVWWSTyq.jpg",
      "source": "TMDb",
      "source_url": "https://www.themoviedb.org/movie/93313",
      "license": "fair_use",
      "attribution": "Howard Productions",
      "is_featured": "False"
    },
    {
      "id": 3939,
      "media_type": "poster",
      "title": "Come and Get It (1936) - Poster",
      "caption": "Theatrical poster for Come and Get It (1936)",
      "url": "https://image.tmdb.org/t/p/original/burlRMIAYGsxOoYpZPAJPhLFL34.jpg",
      "thumbnail_url": "https://image.tmdb.org/t/p/w342/burlRMIAYGsxOoYpZPAJPhLFL34.jpg",
      "source": "TMDb",
      "source_url": "https://www.themoviedb.org/movie/93313",
      "license": "fair_use",
      "attribution": "Howard Productions",
      "is_featured": "False"
    },
    {
      "id": 3940,
      "media_type": "poster",
      "title": "Come and Get It (1936) - Poster",
      "caption": "Theatrical poster for Come and Get It (1936)",
      "url": "https://image.tmdb.org/t/p/original/6Skerdv59Iovdgk6bBYeMwKqxBe.jpg",
      "thumbnail_url": "https://image.tmdb.org/t/p/w342/6Skerdv59Iovdgk6bBYeMwKqxBe.jpg",
      "source": "TMDb",
      "source_url": "https://www.themoviedb.org/movie/93313",
      "license": "fair_use",
      "attribution": "Howard Productions",
      "is_featured": "False"
    },
    {
      "id": 3941,
      "media_type": "still",
      "title": "Come and Get It (1936) - Still",
      "caption": "Scene from Come and Get It (1936)",
      "url": "https://image.tmdb.org/t/p/original/9aiwz7W64ngTBf7v3pSs6lSEj0I.jpg",
      "thumbnail_url": "https://image.tmdb.org/t/p/w780/9aiwz7W64ngTBf7v3pSs6lSEj0I.jpg",
      "source": "TMDb",
      "source_url": "https://www.themoviedb.org/movie/93313",
      "license": "fair_use",
      "attribution": "Howard Productions",
      "is_featured": "False"
    },
    {
      "id": 3942,
      "media_type": "still",
      "title": "Come and Get It (1936) - Still",
      "caption": "Scene from Come and Get It (1936)",
      "url": "https://image.tmdb.org/t/p/original/8Cw4az64XWHCP0Os59JzhUslPH7.jpg",
      "thumbnail_url": "https://image.tmdb.org/t/p/w780/8Cw4az64XWHCP0Os59JzhUslPH7.jpg",
      "source": "TMDb",
      "source_url": "https://www.themoviedb.org/movie/93313",
      "license": "fair_use",
      "attribution": "Howard Productions",
      "is_featured": "False"
    },
    {
      "id": 3943,
      "media_type": "still",
      "title": "Come and Get It (1936) - Still",
      "caption": "Scene from Come and Get It (1936)",
      "url": "https://image.tmdb.org/t/p/original/8hKFtIzjmxAKgNlUnUPjO8Yfqcj.jpg",
      "thumbnail_url": "https://image.tmdb.org/t/p/w780/8hKFtIzjmxAKgNlUnUPjO8Yfqcj.jpg",
      "source": "TMDb",
      "source_url": "https://www.themoviedb.org/movie/93313",
      "license": "fair_use",
      "attribution": "Howard Productions",
      "is_featured": "False"
    },
    {
      "id": 1270,
      "media_type": "still",
      "title": "Frances Farmer and Joel McCrea.png",
      "caption": "Still from Come and Get It",
      "url": "https://upload.wikimedia.org/wikipedia/commons/3/38/Frances_Farmer_and_Joel_McCrea.png",
      "thumbnail_url": "https://upload.wikimedia.org/wikipedia/commons/thumb/3/38/Frances_Farmer_and_Joel_McCrea.png/300px-Frances_Farmer_and_Joel_McCrea.png",
      "source": "Wikimedia Commons",
      "source_url": "https://commons.wikimedia.org/wiki/File:Frances_Farmer_and_Joel_McCrea.png",
      "license": "public_domain",
      "attribution": "Howard Productions",
      "is_featured": "False"
    }
  ],
  "has_media": true,
  "media_count": 10,
  "has_narrative": false,
  "last_updated": "2025-08-04T19:48:13.472502"
}