{
  "id": 276,
  "slug": "laura-1944",
  "title": "Laura",
  "formatted_title": "Laura",
  "html_title": "<span class=\"film-title\">Laura</span>",
  "release_year": 1944,
  "runtime_minutes": 88,
  "country_of_production": "United States",
  "genres": [
    "Film noir"
  ],
  "studio": "20th Century Fox",
  "production_companies": "Twentieth Century-Fox Film Corp.",
  "distribution_companies": "Twentieth Century-Fox Film Corp.",
  "directors": "Otto Preminger",
  "writers": "Jay Dratler|Samuel Hoffenstein|Betty Reinhardt",
  "cast_members": "Gene Tierney|Dana Andrews|Clifton Webb|Vincent Price|Judith Anderson|Dorothy Adams|James Flavin|Clyde Fillmore|Ralph Dunn|Grant Mitchell",
  "color_info": "black-and-white",
  "availability": null,
  "adaptation_notes": null,
  "afi_catalog_id": 24042,
  "source_work": {
    "id": 232,
    "slug": "laura",
    "title": "Laura",
    "formatted_title": "Laura",
    "html_title": "<span class=\"work-title\">Laura</span>",
    "work_type": "novel",
    "publication_year": 1942,
    "plot_summary": null,
    "plot_summary_html": "",
    "literary_significance": null,
    "literary_significance_html": "",
    "adaptation_count": 1,
    "year_to_adaptation": 2
  },
  "author": {
    "id": 59,
    "slug": "vera-caspary",
    "name": "Vera Caspary",
    "birth_year": 1899,
    "death_year": 1987,
    "nationality": "American",
    "film_count": 5
  },
  "other_adaptations": [],
  "adaptation_context": null,
  "media": [
    {
      "id": 760,
      "media_type": "poster",
      "title": "Laura (1944 film poster).jpg",
      "caption": "Theatrical release poster for the 1944 film Laura.",
      "url": "https://upload.wikimedia.org/wikipedia/commons/3/30/Laura_%281944_film_poster%29.jpg",
      "thumbnail_url": "https://upload.wikimedia.org/wikipedia/commons/thumb/3/30/Laura_%281944_film_poster%29.jpg/300px-Laura_%281944_film_poster%29.jpg",
      "source": "Wikimedia Commons",
      "source_url": "https://commons.wikimedia.org/wiki/File:Laura_(1944_film_poster).jpg",
      "license": "public_domain",
      "attribution": "\"Copyright 1944 by Twentieth Century–Fox Film Corp.\"",
      "is_featured": "True"
    },
    {
      "id": 3065,
      "media_type": "poster",
      "title": "Laura (1944) - Poster",
      "caption": "Theatrical poster for Laura (1944)",
      "url": "https://image.tmdb.org/t/p/original/j0zEiFFrdbZnMXqD3piOtZBJeNB.jpg",
      "thumbnail_url": "https://image.tmdb.org/t/p/w342/j0zEiFFrdbZnMXqD3piOtZBJeNB.jpg",
      "source": "TMDb",
      "source_url": "https://www.themoviedb.org/movie/1939",
      "license": "fair_use",
      "attribution": "20th Century Fox",
      "is_featured": "True"
    },
    {
      "id": 3066,
      "media_type": "poster",
      "title": "Laura (1944) - Poster",
      "caption": "Theatrical poster for Laura (1944)",
      "url": "https://image.tmdb.org/t/p/original/utpUn9TdBIx6x2QX91YhYzFZxg1.jpg",
      "thumbnail_url": "https://image.tmdb.org/t/p/w342/utpUn9TdBIx6x2QX91YhYzFZxg1.jpg",
      "source": "TMDb",
      "source_url": "https://www.themoviedb.org/movie/1939",
      "license": "fair_use",
      "attribution": "20th Century Fox",
      "is_featured": "False"
    },
    {
      "id": 3067,
      "media_type": "poster",
      "title": "Laura (1944) - Poster",
      "caption": "Theatrical poster for Laura (1944)",
      "url": "https://image.tmdb.org/t/p/original/q77cs50omKFNL666PnMihl7GPDN.jpg",
      "thumbnail_url": "https://image.tmdb.org/t/p/w342/q77cs50omKFNL666PnMihl7GPDN.jpg",
      "source": "TMDb",
      "source_url": "https://www.themoviedb.org/movie/1939",
      "license": "fair_use",
      "attribution": "20th Century Fox",
      "is_featured": "False"
    },
    {
      "id": 3068,
      "media_type": "poster",
      "title": "Laura (1944) - Poster",
      "caption": "Theatrical poster for Laura (1944)",
      "url": "https://image.tmdb.org/t/p/original/AtZFZSLN3rSMxTQYN9LRpQzDOgh.jpg",
      "thumbnail_url": "https://image.tmdb.org/t/p/w342/AtZFZSLN3rSMxTQYN9LRpQzDOgh.jpg",
      "source": "TMDb",
      "source_url": "https://www.themoviedb.org/movie/1939",
      "license": "fair_use",
      "attribution": "20th Century Fox",
      "is_featured": "False"
    },
    {
      "id": 3069,
      "media_type": "poster",
      "title": "Laura (1944) - Poster",
      "caption": "Theatrical poster for Laura (1944)",
      "url": "https://image.tmdb.org/t/p/original/cEIdgdDa5XIsVHd9g6vhf2wkkZR.jpg",
      "thumbnail_url": "https://image.tmdb.org/t/p/w342/cEIdgdDa5XIsVHd9g6vhf2wkkZR.jpg",
      "source": "TMDb",
      "source_url": "https://www.themoviedb.org/movie/1939",
      "license": "fair_use",
      "attribution": "20th Century Fox",
      "is_featured": "False"
    },
    {
      "id": 3070,
      "media_type": "still",
      "title": "Laura (1944) - Still",
      "caption": "Scene from Laura (1944)",
      "url": "https://image.tmdb.org/t/p/original/d5HjGve67GkNC9lWpzZVKSotLlT.jpg",
      "thumbnail_url": "https://image.tmdb.org/t/p/w780/d5HjGve67GkNC9lWpzZVKSotLlT.jpg",
      "source": "TMDb",
      "source_url": "https://www.themoviedb.org/movie/1939",
      "license": "fair_use",
      "attribution": "20th Century Fox",
      "is_featured": "False"
    },
    {
      "id": 3071,
      "media_type": "still",
      "title": "Laura (1944) - Still",
      "caption": "Scene from Laura (1944)",
      "url": "https://image.tmdb.org/t/p/original/nH8IHZxMIa3u7Vqk4mt4X1Ikycj.jpg",
      "thumbnail_url": "https://image.tmdb.org/t/p/w780/nH8IHZxMIa3u7Vqk4mt4X1Ikycj.jpg",
      "source": "TMDb",
      "source_url": "https://www.themoviedb.org/movie/1939",
      "license": "fair_use",
      "attribution": "20th Century Fox",
      "is_featured": "False"
    },
    {
      "id": 3072,
      "media_type": "still",
      "title": "Laura (1944) - Still",
      "caption": "Scene from Laura (1944)",
      "url": "https://image.tmdb.org/t/p/original/r6GwymahVWaqO7bVfvotvWQPhig.jpg",
      "thumbnail_url": "https://image.tmdb.org/t/p/w780/r6GwymahVWaqO7bVfvotvWQPhig.jpg",
      "source": "TMDb",
      "source_url": "https://www.themoviedb.org/movie/1939",
      "license": "fair_use",
      "attribution": "20th Century Fox",
      "is_featured": "False"
    },
    {
      "id": 758,
      "media_type": "other",
      "title": "Laura (1944) - Trailer.webm",
      "caption": "Original trailer of the film Laura (1944), directed by Otto Preminger.",
      "url": "https://upload.wikimedia.org/wikipedia/commons/a/ad/Laura_%281944%29_-_Trailer.webm",
      "thumbnail_url": "https://upload.wikimedia.org/wikipedia/commons/thumb/a/ad/Laura_%281944%29_-_Trailer.webm/300px-Laura_%281944%29_-_Trailer.jpg",
      "source": "Wikimedia Commons",
      "source_url": "https://commons.wikimedia.org/wiki/File:Laura_(1944)_-_Trailer.webm",
      "license": "public_domain",
      "attribution": "20th Century Fox",
      "is_featured": "False"
    },
    {
      "id": 759,
      "media_type": "still",
      "title": "Laura (1944) trailer 9.jpg",
      "caption": "L. to R. : Clifton Webb, Gene Tierney &amp; Vincent Price in Laura - trailer (cropped screenshot)",
      "url": "https://upload.wikimedia.org/wikipedia/commons/c/c7/Laura_%281944%29_trailer_9.jpg",
      "thumbnail_url": "https://upload.wikimedia.org/wikipedia/commons/thumb/c/c7/Laura_%281944%29_trailer_9.jpg/300px-Laura_%281944%29_trailer_9.jpg",
      "source": "Wikimedia Commons",
      "source_url": "https://commons.wikimedia.org/wiki/File:Laura_(1944)_trailer_9.jpg",
      "license": "public_domain",
      "attribution": "trailer screenshot (20th Century Fox)",
      "is_featured": "False"
    },
    {
      "id": 761,
      "media_type": "still",
      "title": "Laura (1944) - trailer screenshot.jpg",
      "caption": "Screenshot of the trailer of the film Laura.",
      "url": "https://upload.wikimedia.org/wikipedia/commons/2/24/Laura_%281944%29_-_trailer_screenshot.jpg",
      "thumbnail_url": "https://upload.wikimedia.org/wikipedia/commons/thumb/2/24/Laura_%281944%29_-_trailer_screenshot.jpg/300px-Laura_%281944%29_-_trailer_screenshot.jpg",
      "source": "Wikimedia Commons",
      "source_url": "https://commons.wikimedia.org/wiki/File:Laura_(1944)_-_trailer_screenshot.jpg",
      "license": "public_domain",
      "attribution": "20th Century Fox",
      "is_featured": "False"
    }
  ],
  "has_media": true,
  "media_count": 12,
  "has_narrative": false,
  "last_updated": "2025-08-04T19:48:13.472502"
}