{
  "id": 677,
  "slug": "mr-peabody-and-the-mermaid-1948",
  "title": "Mr. Peabody and the Mermaid",
  "formatted_title": "Mr. Peabody and the Mermaid",
  "html_title": "<span class=\"film-title\">Mr. Peabody and the Mermaid</span>",
  "release_year": 1948,
  "runtime_minutes": 89,
  "country_of_production": "United States",
  "genres": [
    "Comedy"
  ],
  "studio": "Inter-John",
  "production_companies": "Inter-John, Inc.",
  "distribution_companies": "Universal Pictures Company, Inc.",
  "directors": "Irving Pichel",
  "writers": "Nunnally Johnson",
  "cast_members": "William Powell|Ann Blyth|Irene Hervey|Andrea King|Clinton Sundberg|Hugh French|Lumsden Hare|Frederick Clarke|James Logan|Mary Field",
  "color_info": "black-and-white",
  "availability": "extant",
  "archive_location": "UCLA Film & Television Archive",
  "adaptation_notes": null,
  "afi_catalog_id": 25647,
  "source_work": {
    "id": 594,
    "slug": "peabodys-mermaid",
    "title": "Peabody's Mermaid",
    "formatted_title": "Peabody's Mermaid",
    "html_title": "<span class=\"work-title\">Peabody's Mermaid</span>",
    "work_type": "novel",
    "publication_year": 1946,
    "plot_summary": null,
    "plot_summary_html": "",
    "literary_significance": null,
    "literary_significance_html": "",
    "adaptation_count": 1,
    "photoplay_edition_count": 0,
    "year_to_adaptation": 2
  },
  "author": {
    "id": 286,
    "slug": "constance-bridges-jones",
    "name": "Constance Bridges Jones",
    "birth_year": null,
    "death_year": null,
    "nationality": "American",
    "film_count": 2
  },
  "other_adaptations": [],
  "adaptation_context": null,
  "media": [
    {
      "id": 4271,
      "media_type": "still",
      "title": "Mr. Peabody and the Mermaid (1948) - Still",
      "caption": "Scene from Mr. Peabody and the Mermaid (1948)",
      "url": "https://image.tmdb.org/t/p/original/iHVjZYTsOcM3yCdwHNkLeG5cV0Q.jpg",
      "thumbnail_url": "https://image.tmdb.org/t/p/w780/iHVjZYTsOcM3yCdwHNkLeG5cV0Q.jpg",
      "source": "TMDb",
      "source_url": "https://www.themoviedb.org/movie/53834",
      "license": "fair_use",
      "attribution": "Inter-John",
      "is_featured": "False"
    },
    {
      "id": 4272,
      "media_type": "still",
      "title": "Mr. Peabody and the Mermaid (1948) - Still",
      "caption": "Scene from Mr. Peabody and the Mermaid (1948)",
      "url": "https://image.tmdb.org/t/p/original/yY79LE5n9CgMafL9FGGYbIjJdGV.jpg",
      "thumbnail_url": "https://image.tmdb.org/t/p/w780/yY79LE5n9CgMafL9FGGYbIjJdGV.jpg",
      "source": "TMDb",
      "source_url": "https://www.themoviedb.org/movie/53834",
      "license": "fair_use",
      "attribution": "Inter-John",
      "is_featured": "False"
    },
    {
      "id": 4273,
      "media_type": "still",
      "title": "Mr. Peabody and the Mermaid (1948) - Still",
      "caption": "Scene from Mr. Peabody and the Mermaid (1948)",
      "url": "https://image.tmdb.org/t/p/original/8iiAATvHDKqFCpBlsatON6ym7Dx.jpg",
      "thumbnail_url": "https://image.tmdb.org/t/p/w780/8iiAATvHDKqFCpBlsatON6ym7Dx.jpg",
      "source": "TMDb",
      "source_url": "https://www.themoviedb.org/movie/53834",
      "license": "fair_use",
      "attribution": "Inter-John",
      "is_featured": "False"
    },
    {
      "id": 4268,
      "media_type": "poster",
      "title": "Mr. Peabody and the Mermaid (1948) - Poster",
      "caption": "Poster for Mr. Peabody and the Mermaid (1948)",
      "url": "https://image.tmdb.org/t/p/original/zi4MRJrM8oBrPheeRhnxSUEBia8.jpg",
      "thumbnail_url": "https://image.tmdb.org/t/p/w342/zi4MRJrM8oBrPheeRhnxSUEBia8.jpg",
      "source": "TMDb",
      "source_url": "https://www.themoviedb.org/movie/53834",
      "license": "fair_use",
      "attribution": "Inter-John",
      "is_featured": "True"
    },
    {
      "id": 4269,
      "media_type": "poster",
      "title": "Mr. Peabody and the Mermaid (1948) - Poster",
      "caption": "Poster for Mr. Peabody and the Mermaid (1948)",
      "url": "https://image.tmdb.org/t/p/original/1JFHdKijoSZ1IO7cNHtmlqiWGu.jpg",
      "thumbnail_url": "https://image.tmdb.org/t/p/w342/1JFHdKijoSZ1IO7cNHtmlqiWGu.jpg",
      "source": "TMDb",
      "source_url": "https://www.themoviedb.org/movie/53834",
      "license": "fair_use",
      "attribution": "Inter-John",
      "is_featured": "False"
    },
    {
      "id": 4270,
      "media_type": "poster",
      "title": "Mr. Peabody and the Mermaid (1948) - Poster",
      "caption": "Poster for Mr. Peabody and the Mermaid (1948)",
      "url": "https://image.tmdb.org/t/p/original/miLIES46JyayMha47KmXyCQAWEU.jpg",
      "thumbnail_url": "https://image.tmdb.org/t/p/w342/miLIES46JyayMha47KmXyCQAWEU.jpg",
      "source": "TMDb",
      "source_url": "https://www.themoviedb.org/movie/53834",
      "license": "fair_use",
      "attribution": "Inter-John",
      "is_featured": "False"
    }
  ],
  "has_media": true,
  "media_count": 6,
  "last_updated": "2025-08-20T23:52:39.994796"
}