{
  "id": 71,
  "slug": "the-branding-iron-1920",
  "title": "The Branding Iron",
  "formatted_title": "The Branding Iron",
  "html_title": "<span class=\"film-title\">The Branding Iron</span>",
  "release_year": 1920,
  "runtime_minutes": 70,
  "country_of_production": "United States",
  "genres": [
    "Drama"
  ],
  "studio": "Goldwyn Pictures",
  "production_companies": "Goldwyn Pictures Corp.; Reginald Barker Productions",
  "distribution_companies": "Goldwyn Distributing Corp.",
  "directors": "Reginald Barker",
  "writers": "J. G. Hawks",
  "cast_members": "Barbara Castleton|James Kirkwood|Russell Simpson|Richard Tucker|Sidney Ainsworth|Gertrude Astor|Albert Roscoe|Marion Colvin|Joan Standing|Louie Cheung",
  "color_info": "black-and-white",
  "availability": "lost",
  "adaptation_notes": null,
  "afi_catalog_id": 17671,
  "source_work": {
    "id": 68,
    "slug": "the-branding-iron",
    "title": "The Branding Iron",
    "formatted_title": "The Branding Iron",
    "html_title": "<span class=\"work-title\">The Branding Iron</span>",
    "work_type": "novel",
    "publication_year": 1919,
    "plot_summary": null,
    "plot_summary_html": "",
    "literary_significance": null,
    "literary_significance_html": "",
    "adaptation_count": 1,
    "year_to_adaptation": 1
  },
  "author": {
    "id": 32,
    "slug": "katharine-newlin-burt",
    "name": "Katharine Newlin Burt",
    "birth_year": 1882,
    "death_year": 1977,
    "nationality": "American",
    "film_count": 7
  },
  "other_adaptations": [],
  "adaptation_context": null,
  "media": [
    {
      "id": 2472,
      "media_type": "poster",
      "title": "The Branding Iron (1920) - Poster",
      "caption": "Theatrical poster for The Branding Iron (1920)",
      "url": "https://image.tmdb.org/t/p/original/dIzNe9VxXkIY0CkkVWrLuFhp86q.jpg",
      "thumbnail_url": "https://image.tmdb.org/t/p/w342/dIzNe9VxXkIY0CkkVWrLuFhp86q.jpg",
      "source": "TMDb",
      "source_url": "https://www.themoviedb.org/movie/314162",
      "license": "fair_use",
      "attribution": "Goldwyn Pictures",
      "is_featured": "False"
    },
    {
      "id": 2473,
      "media_type": "poster",
      "title": "The Branding Iron (1920) - Poster",
      "caption": "Theatrical poster for The Branding Iron (1920)",
      "url": "https://image.tmdb.org/t/p/original/1QXEM0wUAFdSh2FDuO7ZLMEH6ow.jpg",
      "thumbnail_url": "https://image.tmdb.org/t/p/w342/1QXEM0wUAFdSh2FDuO7ZLMEH6ow.jpg",
      "source": "TMDb",
      "source_url": "https://www.themoviedb.org/movie/314162",
      "license": "fair_use",
      "attribution": "Goldwyn Pictures",
      "is_featured": "False"
    },
    {
      "id": 194,
      "media_type": "advertisement",
      "title": "The Branding Iron by Reginald Barker.png",
      "caption": "Ad for the film The Branding Iron (1920) directed by Reginald Barker",
      "url": "https://upload.wikimedia.org/wikipedia/commons/9/96/The_Branding_Iron_by_Reginald_Barker.png",
      "thumbnail_url": "https://upload.wikimedia.org/wikipedia/commons/thumb/9/96/The_Branding_Iron_by_Reginald_Barker.png/300px-The_Branding_Iron_by_Reginald_Barker.png",
      "source": "Wikimedia Commons",
      "source_url": "https://commons.wikimedia.org/wiki/File:The_Branding_Iron_by_Reginald_Barker.png",
      "license": "public_domain",
      "attribution": "Goldwyn Pictures",
      "is_featured": "False"
    },
    {
      "id": 185,
      "media_type": "advertisement",
      "title": "The Branding Iron (1920) - 8.jpg",
      "caption": "Newspaper advertisement for the American drama film The Branding Iron (1920), on page 2 of the October 20, 1920 The Duluth Herald.",
      "url": "https://upload.wikimedia.org/wikipedia/commons/8/8f/The_Branding_Iron_%281920%29_-_8.jpg",
      "thumbnail_url": "https://upload.wikimedia.org/wikipedia/commons/thumb/8/8f/The_Branding_Iron_%281920%29_-_8.jpg/300px-The_Branding_Iron_%281920%29_-_8.jpg",
      "source": "Wikimedia Commons",
      "source_url": "https://commons.wikimedia.org/wiki/File:The_Branding_Iron_(1920)_-_8.jpg",
      "license": "public_domain",
      "attribution": "Reginald Barker Productions / Goldwyn Pictures Corporation",
      "is_featured": "False"
    },
    {
      "id": 186,
      "media_type": "advertisement",
      "title": "The Branding Iron (1920) - 6.jpg",
      "caption": "Advertisement for the American drama film The Branding Iron (1920) with Barbara Castleton and James Kirkwood, on page 4 of the September 18, 1920 Exhibitors Herald.",
      "url": "https://upload.wikimedia.org/wikipedia/commons/2/2f/The_Branding_Iron_%281920%29_-_6.jpg",
      "thumbnail_url": "https://upload.wikimedia.org/wikipedia/commons/thumb/2/2f/The_Branding_Iron_%281920%29_-_6.jpg/300px-The_Branding_Iron_%281920%29_-_6.jpg",
      "source": "Wikimedia Commons",
      "source_url": "https://commons.wikimedia.org/wiki/File:The_Branding_Iron_(1920)_-_6.jpg",
      "license": "public_domain",
      "attribution": "Reginald Barker Productions / Goldwyn Pictures Corporation",
      "is_featured": "False"
    },
    {
      "id": 187,
      "media_type": "still",
      "title": "The Branding Iron (1920) - 3.jpg",
      "caption": "Scenario writer J. G. Hawks (1874 – 1940) (seated) discussing a scene with director Reginald Barker on the set of the American drama film The Branding Iron (1920), on page 77 of the August 21, 1920 Exhibitors Herald.",
      "url": "https://upload.wikimedia.org/wikipedia/commons/5/58/The_Branding_Iron_%281920%29_-_3.jpg",
      "thumbnail_url": "https://upload.wikimedia.org/wikipedia/commons/thumb/5/58/The_Branding_Iron_%281920%29_-_3.jpg/300px-The_Branding_Iron_%281920%29_-_3.jpg",
      "source": "Wikimedia Commons",
      "source_url": "https://commons.wikimedia.org/wiki/File:The_Branding_Iron_(1920)_-_3.jpg",
      "license": "public_domain",
      "attribution": "Reginald Barker Productions / Goldwyn Pictures Corporation",
      "is_featured": "False"
    },
    {
      "id": 188,
      "media_type": "still",
      "title": "The Branding Iron (1920) - 4.jpg",
      "caption": "Still from the American drama film The Branding Iron (1920) with an unidentified actor and Barbara Castleton, on page 100 of the August 21, 1920 Exhibitors Herald.",
      "url": "https://upload.wikimedia.org/wikipedia/commons/6/62/The_Branding_Iron_%281920%29_-_4.jpg",
      "thumbnail_url": "https://upload.wikimedia.org/wikipedia/commons/thumb/6/62/The_Branding_Iron_%281920%29_-_4.jpg/300px-The_Branding_Iron_%281920%29_-_4.jpg",
      "source": "Wikimedia Commons",
      "source_url": "https://commons.wikimedia.org/wiki/File:The_Branding_Iron_(1920)_-_4.jpg",
      "license": "public_domain",
      "attribution": "Reginald Barker Productions / Goldwyn Pictures Corporation",
      "is_featured": "False"
    },
    {
      "id": 189,
      "media_type": "still",
      "title": "The Branding Iron (1920) - 2.jpg",
      "caption": "Still from the American drama film The Branding Iron (1920) with Barbara Castleton, on page 63 of the August 7, 1920 Exhibitors Herald.",
      "url": "https://upload.wikimedia.org/wikipedia/commons/3/38/The_Branding_Iron_%281920%29_-_2.jpg",
      "thumbnail_url": "https://upload.wikimedia.org/wikipedia/commons/thumb/3/38/The_Branding_Iron_%281920%29_-_2.jpg/300px-The_Branding_Iron_%281920%29_-_2.jpg",
      "source": "Wikimedia Commons",
      "source_url": "https://commons.wikimedia.org/wiki/File:The_Branding_Iron_(1920)_-_2.jpg",
      "license": "public_domain",
      "attribution": "Reginald Barker Productions / Goldwyn Pictures Corporation",
      "is_featured": "False"
    },
    {
      "id": 190,
      "media_type": "still",
      "title": "The Branding Iron (1920) - 5.jpg",
      "caption": "Still from the American drama film The Branding Iron (1920) with Barbara Castleton, on page 46 of the August 28, 1920 Exhibitors Herald.",
      "url": "https://upload.wikimedia.org/wikipedia/commons/8/8f/The_Branding_Iron_%281920%29_-_5.jpg",
      "thumbnail_url": "https://upload.wikimedia.org/wikipedia/commons/thumb/8/8f/The_Branding_Iron_%281920%29_-_5.jpg/300px-The_Branding_Iron_%281920%29_-_5.jpg",
      "source": "Wikimedia Commons",
      "source_url": "https://commons.wikimedia.org/wiki/File:The_Branding_Iron_(1920)_-_5.jpg",
      "license": "public_domain",
      "attribution": "Reginald Barker Productions / Goldwyn Pictures Corporation",
      "is_featured": "False"
    },
    {
      "id": 191,
      "media_type": "still",
      "title": "The Branding Iron (1920) - Barbara Castleton.jpg",
      "caption": "Still from the American drama film The Branding Iron (1920) with Barbara Castleton, from an article on film censorship on page 40 of the October 1922 Photoplay. The caption noted that this scene had been cut in Pennsylvania because of its nudity, but then that state board banned the entire film because it dealt with the topic of infidelity.",
      "url": "https://upload.wikimedia.org/wikipedia/commons/d/d2/The_Branding_Iron_%281920%29_-_Barbara_Castleton.jpg",
      "thumbnail_url": "https://upload.wikimedia.org/wikipedia/commons/thumb/d/d2/The_Branding_Iron_%281920%29_-_Barbara_Castleton.jpg/300px-The_Branding_Iron_%281920%29_-_Barbara_Castleton.jpg",
      "source": "Wikimedia Commons",
      "source_url": "https://commons.wikimedia.org/wiki/File:The_Branding_Iron_(1920)_-_Barbara_Castleton.jpg",
      "license": "public_domain",
      "attribution": "Reginald Barker Productions / Goldwyn Pictures Corporation",
      "is_featured": "False"
    },
    {
      "id": 192,
      "media_type": "still",
      "title": "The Branding Iron (1920) 1.jpg",
      "caption": "James Kirkwood, Sr. and Barbara Castleton in The Branding Iron (1920).",
      "url": "https://upload.wikimedia.org/wikipedia/commons/b/bf/The_Branding_Iron_%281920%29_1.jpg",
      "thumbnail_url": "https://upload.wikimedia.org/wikipedia/commons/thumb/b/bf/The_Branding_Iron_%281920%29_1.jpg/300px-The_Branding_Iron_%281920%29_1.jpg",
      "source": "Wikimedia Commons",
      "source_url": "https://commons.wikimedia.org/wiki/File:The_Branding_Iron_(1920)_1.jpg",
      "license": "public_domain",
      "attribution": "film screenshot (Goldwyn Pictures Corporation)",
      "is_featured": "False"
    },
    {
      "id": 193,
      "media_type": "still",
      "title": "The Branding Iron (1920) - 7.jpg",
      "caption": "Still from the American drama film The Branding Iron (1920) with Barbara Castleton just after the branding, on page 88 of the October 23, 1920 Exhibitors Herald.",
      "url": "https://upload.wikimedia.org/wikipedia/commons/3/3e/The_Branding_Iron_%281920%29_-_7.jpg",
      "thumbnail_url": "https://upload.wikimedia.org/wikipedia/commons/thumb/3/3e/The_Branding_Iron_%281920%29_-_7.jpg/300px-The_Branding_Iron_%281920%29_-_7.jpg",
      "source": "Wikimedia Commons",
      "source_url": "https://commons.wikimedia.org/wiki/File:The_Branding_Iron_(1920)_-_7.jpg",
      "license": "public_domain",
      "attribution": "Reginald Barker Productions / Goldwyn Pictures Corporation",
      "is_featured": "False"
    }
  ],
  "has_media": true,
  "media_count": 12,
  "has_narrative": false,
  "last_updated": "2025-08-04T19:48:13.472502"
}